chattyterminal/__init__.py
chattyterminal/go.py
chattyterminal-0.0.0.dev0.dist-info/LICENSE
chattyterminal-0.0.0.dev0.dist-info/METADATA
chattyterminal-0.0.0.dev0.dist-info/WHEEL
chattyterminal-0.0.0.dev0.dist-info/top_level.txt
chattyterminal-0.0.0.dev0.dist-info/RECORD
