Metadata-Version: 2.1
Name: chattyterminal
Version: 0.0.0.dev0
Summary: A cli application for invoking generative AI
Author-email: Shuffled Bits <shuffled.bits.j5oj9@slmail.me>
Maintainer-email: Shuffled Bits <shuffled.bits.j5oj9@slmail.me>
Keywords: ai
Classifier: Development Status :: 1 - Planning
Classifier: Programming Language :: Python :: 3
Classifier: License :: OSI Approved :: MIT License
Classifier: Operating System :: OS Independent
Requires-Python: >=3.9
License-File: LICENSE
